Metadata-Version: 2.1
Name: timea-lib
Version: 0.2
Summary: This is  test project!
Home-page: http://google.com
Author: Timea
Author-email: timea@mail.com
License: UNKNOWN
Platform: UNKNOWN
Requires-Python: >=3.10
